ratemate/__init__.py
ratemate/ratelim.py
ratemate-0.1.0.dist-info/LICENSE
ratemate-0.1.0.dist-info/WHEEL
ratemate-0.1.0.dist-info/METADATA
ratemate-0.1.0.dist-info/RECORD
