Metadata-Version: 2.1
Name: ratemate
Version: 0.1.0
Summary: A python rate limiter module with multi-process support and a simple, intuitive API
Author: Robert Lechte
Author-email: robert.lechte@dpc.vic.gov.au
Requires-Python: >=3.7
Classifier: Programming Language :: Python :: 3
Classifier: Programming Language :: Python :: 3.7
